Metadata-Version: 1.1
Name: workerpool
Version: 0.9.4
Summary: Module for distributing jobs to a pool of worker threads.
Home-page: https://github.com/shazow/workerpool
Author: Andrey Petrov
Author-email: andrey.petrov@shazow.net
License: MIT
Keywords: pooling threading jobs
Platform: UNKNOWN
Classifier: Intended Audience :: Developers
Classifier: Programming Language :: Python :: 2
Classifier: Programming Language :: Python :: 3
Classifier: Topic :: Software Development :: Libraries :: Python Modules
Classifier: License :: OSI Approved :: MIT License
Classifier: Operating System :: OS Independent
